{
  "_class": "group",
  "booleanOperation": 0,
  "clippingMaskMode": 0,
  "do_objectID": "5A36CB92-5642-4747-99A6-184820C2ED5E",
  "exportOptions": {
    "_class": "exportOptions",
    "exportFormats": [
    ],
    "includedLayerIds": [
    ],
    "layerOptions": 0,
    "shouldTrim": false
  },
  "frame": {
    "_class": "rect",
    "constrainProportions": false,
    "height": 220,
    "width": 86,
    "x": 0,
    "y": 37
  },
  "groupLayout": {
    "_class": "MSImmutableFreeformGroupLayout"
  },
  "hasClickThrough": false,
  "hasClippingMask": false,
  "isFixedToViewport": false,
  "isFlippedHorizontal": false,
  "isFlippedVertical": false,
  "isLocked": false,
  "isVisible": true,
  "layerListExpandedType": 0,
  "layers": [
    {
      "class": "symbolInstance",
      "id": "A8BD3225-2376-428E-823E-8D7D4CB52472"
    },
    {
      "class": "symbolInstance",
      "id": "6F02CFFC-28FC-45BF-8866-A0D1909DFEC3"
    },
    {
      "class": "symbolInstance",
      "id": "13BB3939-02EA-45B0-B932-CF80E3D923DD"
    },
    {
      "class": "symbolInstance",
      "id": "AB2D61F0-3B66-4499-97F2-85CA1A2B3CDC"
    },
    {
      "class": "symbolInstance",
      "id": "139683B9-AA35-45C8-BC48-E6F76DC67A57"
    }
  ],
  "name": "Blue Button",
  "nameIsFixed": true,
  "resizingConstraint": 63,
  "resizingType": 0,
  "rotation": 0,
  "shouldBreakMaskChain": false,
  "style": {
    "_class": "style",
    "endMarkerType": 0,
    "miterLimit": 10,
    "startMarkerType": 0,
    "windingRule": 1
  }
}