{
  "_class": "symbolInstance",
  "booleanOperation": 0,
  "clippingMaskMode": 0,
  "do_objectID": "8F4EAB44-424E-43DC-8EA8-4B97AD7657AF",
  "exportOptions": {
    "_class": "exportOptions",
    "exportFormats": [
    ],
    "includedLayerIds": [
    ],
    "layerOptions": 0,
    "shouldTrim": false
  },
  "frame": {
    "_class": "rect",
    "constrainProportions": false,
    "height": 36,
    "width": 36,
    "x": 0,
    "y": 0
  },
  "hasClippingMask": false,
  "horizontalSpacing": 0,
  "isFixedToViewport": false,
  "isFlippedHorizontal": false,
  "isFlippedVertical": false,
  "isLocked": false,
  "isVisible": true,
  "layerListExpandedType": 0,
  "name": "Icon",
  "nameIsFixed": true,
  "overrideValues": [
    {
      "_class": "overrideValue",
      "overrideName": "1A049390-AAC3-4B69-9A33-076DEE2E10A7_symbolID",
      "value": "ADF664A0-AC6D-4174-8AA7-3DB9FC5E81E0"
    },
    {
      "_class": "overrideValue",
      "overrideName": "51F50CC9-3352-43D7-9316-D3D67B98EF66_symbolID",
      "value": "C5C431D0-57D3-4DC9-AF1D-F53F49A96A1C"
    },
    {
      "_class": "overrideValue",
      "overrideName": "51F50CC9-3352-43D7-9316-D3D67B98EF66/A3400162-20B4-42B6-8092-8A264C252213_symbolID",
      "value": "C3903B39-5BB0-4EA4-8779-97A06C425DDD"
    },
    {
      "_class": "overrideValue",
      "overrideName": "51F50CC9-3352-43D7-9316-D3D67B98EF66/410F5543-D1A5-48C3-A21E-FA3E5123C848_symbolID",
      "value": ""
    },
    {
      "_class": "overrideValue",
      "overrideName": "7163FE7D-3097-4479-A6A7-3B675628A831_symbolID",
      "value": "4C36CBD3-055C-4B4E-A664-B3E0FBA807BC"
    }
  ],
  "resizingConstraint": 63,
  "resizingType": 0,
  "rotation": 0,
  "scale": 1,
  "shouldBreakMaskChain": false,
  "style": {
    "_class": "style",
    "endMarkerType": 0,
    "miterLimit": 10,
    "startMarkerType": 0,
    "windingRule": 1
  },
  "symbolID": "84A69888-0118-48D6-BEBB-4CA46EB67047",
  "verticalSpacing": 0
}