{
  "_class": "group",
  "booleanOperation": 0,
  "clippingMaskMode": 0,
  "do_objectID": "42AAA5E0-3635-4F12-A288-4155C4BD97C6",
  "exportOptions": {
    "_class": "exportOptions",
    "exportFormats": [
    ],
    "includedLayerIds": [
    ],
    "layerOptions": 0,
    "shouldTrim": false
  },
  "frame": {
    "_class": "rect",
    "constrainProportions": false,
    "height": 24,
    "width": 24,
    "x": -997,
    "y": -945.5
  },
  "groupLayout": {
    "_class": "MSImmutableFreeformGroupLayout"
  },
  "hasClickThrough": false,
  "hasClippingMask": false,
  "isFixedToViewport": false,
  "isFlippedHorizontal": false,
  "isFlippedVertical": false,
  "isLocked": false,
  "isVisible": true,
  "layerListExpandedType": 0,
  "layers": [
    {
      "class": "oval",
      "id": "80934086-4AC6-485E-A0C3-A345D798E5AE"
    },
    {
      "class": "text",
      "id": "F6DF735D-3A3C-449F-A08C-8998AEA5F964"
    }
  ],
  "name": "ui green circular label",
  "nameIsFixed": false,
  "resizingConstraint": 63,
  "resizingType": 0,
  "rotation": 0,
  "shouldBreakMaskChain": false,
  "style": {
    "_class": "style",
    "endMarkerType": 0,
    "miterLimit": 10,
    "startMarkerType": 0,
    "windingRule": 1
  }
}