{
  "_class": "symbolMaster",
  "allowsOverrides": true,
  "backgroundColor": {
    "_class": "color",
    "alpha": 1,
    "blue": 1,
    "green": 1,
    "red": 1
  },
  "booleanOperation": 0,
  "changeIdentifier": 5427,
  "clippingMaskMode": 0,
  "do_objectID": "F22329B6-FE2D-4CE2-8AA4-522DA6ACFFCB",
  "exportOptions": {
    "_class": "exportOptions",
    "exportFormats": [
    ],
    "includedLayerIds": [
    ],
    "layerOptions": 0,
    "shouldTrim": false
  },
  "frame": {
    "_class": "rect",
    "constrainProportions": false,
    "height": 30,
    "width": 66,
    "x": 244,
    "y": 297
  },
  "groupLayout": {
    "_class": "MSImmutableFreeformGroupLayout"
  },
  "hasBackgroundColor": false,
  "hasClickThrough": true,
  "hasClippingMask": false,
  "horizontalRulerData": {
    "_class": "rulerData",
    "base": 0,
    "guides": [
    ]
  },
  "includeBackgroundColorInExport": true,
  "includeBackgroundColorInInstance": false,
  "includeInCloudUpload": true,
  "isFixedToViewport": false,
  "isFlippedHorizontal": false,
  "isFlippedVertical": false,
  "isFlowHome": false,
  "isLocked": false,
  "isVisible": true,
  "layerListExpandedType": 0,
  "layers": [
    {
      "class": "symbolInstance",
      "id": "D0341B08-67D4-444D-8FD8-312DBA7DF504"
    },
    {
      "class": "symbolInstance",
      "id": "9E6A4234-9121-4A0A-8B48-B1DAF6319A10"
    }
  ],
  "name": "Button/Default/Small/Icon Only",
  "nameIsFixed": true,
  "overrideProperties": [
    {
      "_class": "MSImmutableOverrideProperty",
      "canOverride": true,
      "overrideName": "D0341B08-67D4-444D-8FD8-312DBA7DF504_symbolID"
    },
    {
      "_class": "MSImmutableOverrideProperty",
      "canOverride": true,
      "overrideName": "9E6A4234-9121-4A0A-8B48-B1DAF6319A10_symbolID"
    }
  ],
  "resizesContent": false,
  "resizingConstraint": 63,
  "resizingType": 0,
  "rotation": 0,
  "shouldBreakMaskChain": true,
  "style": {
    "_class": "style",
    "endMarkerType": 0,
    "miterLimit": 10,
    "startMarkerType": 0,
    "windingRule": 1
  },
  "symbolID": "F4170CF6-FC32-404C-91F3-3807BBC6CD40",
  "verticalRulerData": {
    "_class": "rulerData",
    "base": 0,
    "guides": [
    ]
  }
}