{
  "_class": "symbolInstance",
  "booleanOperation": 0,
  "clippingMaskMode": 0,
  "do_objectID": "53343ABC-7994-429F-B8E9-6362BF654311",
  "exportOptions": {
    "_class": "exportOptions",
    "do_objectID": "DE0090E8-6C7D-4424-8B09-5033D2D678E1",
    "exportFormats": [
    ],
    "includedLayerIds": [
    ],
    "layerOptions": 0,
    "shouldTrim": false
  },
  "frame": {
    "_class": "rect",
    "constrainProportions": false,
    "do_objectID": "0629E518-8981-4448-87C1-556DC608D79E",
    "height": 16,
    "width": 16,
    "x": 16,
    "y": 10
  },
  "hasClippingMask": false,
  "horizontalSpacing": 0,
  "isFixedToViewport": false,
  "isFlippedHorizontal": false,
  "isFlippedVertical": false,
  "isLocked": false,
  "isVisible": true,
  "layerListExpandedType": 0,
  "name": "Icon (Left)",
  "nameIsFixed": true,
  "overrideValues": [
    {
      "_class": "overrideValue",
      "overrideName": "43276E30-4DC8-4633-8E77-6C876FC376C2_symbolID",
      "value": "79ECCD6E-B5CF-441E-B034-1D0429EC1AB3"
    }
  ],
  "resizingConstraint": 9,
  "resizingType": 0,
  "rotation": 0,
  "scale": 1,
  "shouldBreakMaskChain": false,
  "style": {
    "_class": "style",
    "do_objectID": "96AB1C30-1AED-421A-ABE3-B4FCAA219746",
    "endMarkerType": 0,
    "miterLimit": 10,
    "startMarkerType": 0,
    "windingRule": 1
  },
  "symbolID": "1A0C7E7E-8CDB-438B-84AD-1A641939255A",
  "verticalSpacing": 0
}