{
  "_class": "group",
  "booleanOperation": 0,
  "clippingMaskMode": 0,
  "do_objectID": "730126E4-0206-4DB4-A32E-E170469A733B",
  "exportOptions": {
    "_class": "exportOptions",
    "exportFormats": [
    ],
    "includedLayerIds": [
    ],
    "layerOptions": 0,
    "shouldTrim": false
  },
  "frame": {
    "_class": "rect",
    "constrainProportions": false,
    "height": 5,
    "width": 11,
    "x": -3,
    "y": 8
  },
  "groupLayout": {
    "_class": "MSImmutableFreeformGroupLayout"
  },
  "hasClickThrough": false,
  "hasClippingMask": false,
  "isFixedToViewport": false,
  "isFlippedHorizontal": false,
  "isFlippedVertical": false,
  "isLocked": false,
  "isVisible": true,
  "layerListExpandedType": 2,
  "layers": [
    {
      "class": "triangle",
      "id": "381BC25F-C51D-4106-A6F1-927CFF3BD89F"
    },
    {
      "class": "symbolInstance",
      "id": "18BC0CFA-870C-4882-BF7A-244CC6EB517C"
    }
  ],
  "name": "Color",
  "nameIsFixed": false,
  "resizingConstraint": 41,
  "resizingType": 0,
  "rotation": 90,
  "shouldBreakMaskChain": false,
  "style": {
    "_class": "style",
    "endMarkerType": 0,
    "miterLimit": 10,
    "startMarkerType": 0,
    "windingRule": 1
  }
}